v2donut/__init__.py
v2donut/__main__.py
v2donut/appsettings.py
v2donut/ping.py
v2donut/subscription.py
v2donut/utils.py
v2donut/v2conf.py
v2donut/v2donut.json
v2donut-1.0.3.dist-info/LICENSE
v2donut-1.0.3.dist-info/METADATA
v2donut-1.0.3.dist-info/WHEEL
v2donut-1.0.3.dist-info/top_level.txt
v2donut-1.0.3.dist-info/RECORD
