Metadata-Version: 2.1
Name: v2donut
Version: 1.0.3
Summary: 自动获取、设置延迟最低的 V2Ray 节点
Home-page: https://github.com/drawmoon/v2donut
Author: drawmoon
Author-email: 1340260725@qq.com
License: MIT License
Platform: UNKNOWN
Classifier: Programming Language :: Python :: 3.10
Classifier: License :: OSI Approved :: MIT License
Classifier: Operating System :: OS Independent
Requires-Python: >=3.7
License-File: LICENSE
Requires-Dist: httpx
Requires-Dist: pythonping
